./.gitignore
./LICENSE
./PKG-INFO
./README.md
./downloader.py
./player.py
./pyproject.toml
playback_tui-1.4.2.dist-info/METADATA
playback_tui-1.4.2.dist-info/WHEEL
playback_tui-1.4.2.dist-info/entry_points.txt
playback_tui-1.4.2.dist-info/licenses/LICENSE
playback_tui-1.4.2.dist-info/RECORD
