Metadata-Version: 2.4
Name: playback-tui
Version: 1.4.2
Summary: A terminal-based music player with playlist management and downloading capabilities
Project-URL: Homepage, https://playback-tui.ashankbehara.com
Project-URL: Bug Reports, https://playback-tui.ashankbehara.com
Project-URL: Source, https://github.com/abehara2/playlist
Author-email: Ashank Behara <ashank.behara@gmail.com>
License: MIT
License-File: LICENSE
Keywords: downloader,music,player,playlist,soundcloud,spotify,terminal,tui
Classifier: Development Status :: 4 - Beta
Classifier: Environment :: Console
Classifier: Intended Audience :: End Users/Desktop
Classifier: Operating System :: OS Independent
Classifier: Programming Language :: Python :: 3
Classifier: Programming Language :: Python :: 3.10
Classifier: Programming Language :: Python :: 3.11
Classifier: Programming Language :: Python :: 3.12
Classifier: Topic :: Multimedia :: Sound/Audio :: Players
Classifier: Topic :: Terminals
Requires-Python: >=3.10
Requires-Dist: mutagen>=1.47.0
Requires-Dist: pygame>=2.6.0
Requires-Dist: pynput>=1.7.6
Requires-Dist: requests>=2.32.0
Requires-Dist: spotipy>=2.25.0
Requires-Dist: textual>=5.3.0
Requires-Dist: yt-dlp>=2024.0.0
